maybenot/__init__.py
maybenot/filters/__init__.py
maybenot/filters/change_owner.py
maybenot/filters/change_permissions.py
maybenot/filters/create_directory.py
maybenot/filters/create_link.py
maybenot/filters/create_write_file.py
maybenot/filters/delete.py
maybenot/filters/move.py
maybenot/maybe.py
maybenot/process.py
maybenot-0.5.0rc1.dist-info/LICENSE
maybenot-0.5.0rc1.dist-info/METADATA
maybenot-0.5.0rc1.dist-info/WHEEL
maybenot-0.5.0rc1.dist-info/entry_points.txt
maybenot-0.5.0rc1.dist-info/RECORD
