Metadata-Version: 2.1
Name: maybenot
Version: 0.5.0rc1
Summary: See what a program does before deciding whether you really want it to happen.
Home-page: https://github.com/histrio/maybenot
License: GPLv3
Keywords: command preview,system calls interception,file system operations simulation,dry run utility
Author: Philipp Emanuel Weidmann
Author-email: pew@worldwidemann.com
Requires-Python: >=3.8,<4.0
Classifier: Development Status :: 3 - Alpha
Classifier: Intended Audience :: End Users/Desktop
Classifier: Intended Audience :: System Administrators
Classifier: License :: OSI Approved :: GNU General Public License v3 (GPLv3)
Classifier: License :: Other/Proprietary License
Classifier: Operating System :: POSIX :: Linux
Classifier: Programming Language :: Python :: 3
Classifier: Programming Language :: Python :: 3.8
Classifier: Programming Language :: Python :: 3.9
Classifier: Programming Language :: Python :: 3.10
Classifier: Programming Language :: Python :: 3.11
Classifier: Programming Language :: Python :: 3.12
Classifier: Topic :: Utilities
Requires-Dist: blessings (>=1.7,<2.0)
Requires-Dist: python-ptrace (>=0.9.8,<0.10.0)
Project-URL: Documentation, https://histrio.github.io/maybenot/
Project-URL: Repository, https://github.com/histrio/maybenot
